{"v":"5.10.2","fr":60,"ip":0,"op":60,"w":430,"h":430,"nm":"wired-flat-237-star-rating-morph","ddd":0,"assets":[{"id":"comp_1","nm":"hover-pinch","fr":60,"layers":[{"ddd":0,"ind":1,"ty":4,"nm":"Star shadow","parent":2,"sr":1,"ks":{"o":{"a":0,"k":50,"ix":11},"r":{"a":0,"k":0,"ix":10},"p":{"a":0,"k":[-88.55,63.799,0],"ix":2,"l":2},"a":{"a":0,"k":[0,0,0],"ix":1,"l":2},"s":{"a":0,"k":[100,100,100],"ix":6,"l":2}},"ao":0,"shapes":[{"ty":"gr","it":[{"ind":0,"ty":"sh","ix":1,"ks":{"a":1,"k":[{"i":{"x":0.318,"y":1},"o":{"x":0.333,"y":0},"t":0,"s":[{"i":[[0,0],[0,0],[0.226,-0.655],[0.575,-0.386],[0,0],[0.304,-0.854]],"o":[[0,0],[0.216,0.659],[-0.226,0.655],[0,0],[-0.732,0.534],[0,0]],"v":[[-88.624,12.795],[88.466,-39.915],[88.451,-37.89],[87.216,-36.285],[-16.664,37.785],[-18.254,39.915]],"c":true}]},{"i":{"x":0.667,"y":1},"o":{"x":0.688,"y":0},"t":8,"s":[{"i":[[0,0],[0,0],[0.249,-0.723],[0.635,-0.426],[0,0],[0.336,-0.942]],"o":[[0,0],[0.238,0.727],[-0.249,0.723],[0,0],[-0.808,0.59],[0,0]],"v":[[-70.23,-3.481],[125.245,-61.663],[125.228,-59.428],[123.865,-57.656],[9.201,24.103],[7.446,26.454]],"c":true}]},{"i":{"x":0.667,"y":1},"o":{"x":0.333,"y":0},"t":22,"s":[{"i":[[0,0],[0,0],[0.181,-0.527],[0.463,-0.311],[0,0],[0.244,-0.686]],"o":[[0,0],[0.173,0.53],[-0.181,0.527],[0,0],[-0.589,0.43],[0,0]],"v":[[-88.611,10.151],[53.8,-32.237],[53.788,-30.608],[52.795,-29.318],[-30.743,30.248],[-32.022,31.961]],"c":true}]},{"t":38,"s":[{"i":[[0,0],[0,0],[0.226,-0.655],[0.575,-0.386],[0,0],[0.304,-0.854]],"o":[[0,0],[0.216,0.659],[-0.226,0.655],[0,0],[-0.732,0.534],[0,0]],"v":[[-88.624,12.795],[88.466,-39.915],[88.451,-37.89],[87.216,-36.285],[-16.664,37.785],[-18.254,39.915]],"c":true}]}],"ix":2},"nm":"Path 1","mn":"ADBE Vector Shape - Group","hd":false},{"ty":"fl","c":{"a":0,"k":[1,0.78,0.22,1],"ix":4,"x":"var $bm_rt;\n$bm_rt = comp('wired-flat-237-star-rating-morph').layer('control').effect('primary')('Color');"},"o":{"a":0,"k":100,"ix":5},"r":1,"bm":0,"nm":".primary","mn":"ADBE Vector Graphic - Fill","hd":false,"cl":"primary"},{"ty":"tr","p":{"a":0,"k":[177.156,-63.094],"ix":2},"a":{"a":0,"k":[0,0],"ix":1},"s":{"a":0,"k":[100,100],"ix":3},"r":{"a":0,"k":0,"ix":6},"o":{"a":0,"k":100,"ix":7},"sk":{"a":0,"k":0,"ix":4},"sa":{"a":0,"k":0,"ix":5},"nm":"Transform"}],"nm":"Vector 4","np":2,"cix":2,"bm":0,"ix":1,"mn":"ADBE Vector Group","hd":false},{"ty":"gr","it":[{"ind":0,"ty":"sh","ix":1,"ks":{"a":1,"k":[{"i":{"x":0.318,"y":1},"o":{"x":0.333,"y":0},"t":0,"s":[{"i":[[0.557,0.399],[0,0],[0,0],[0.906,0],[0,0],[0,0],[0.685,-0.013]],"o":[[0,0],[0,0],[-0.732,-0.533],[0,0],[0,0],[-0.541,0.419],[-0.685,0.013]],"v":[[50.65,77.777],[-51.93,-2.993],[-51.93,-2.993],[-54.45,-3.813],[-53.21,-78.373],[54.45,77.707],[52.562,78.372]],"c":true}]},{"i":{"x":0.667,"y":1},"o":{"x":0.688,"y":0},"t":8,"s":[{"i":[[0.614,0.44],[0,0],[0,0],[1,0],[0,0],[0,0],[0.756,-0.014]],"o":[[0,0],[0,0],[-0.808,-0.588],[0,0],[0,0],[-0.598,0.463],[-0.756,0.014]],"v":[[79.834,77.714],[-33.396,-11.441],[-33.396,-11.441],[-36.177,-12.346],[-34.809,-94.647],[84.028,77.637],[81.944,78.371]],"c":true}]},{"i":{"x":0.667,"y":1},"o":{"x":0.333,"y":0},"t":22,"s":[{"i":[[0.448,0.321],[0,0],[0,0],[0.728,0],[0,0],[0,0],[0.551,-0.01]],"o":[[0,0],[0,0],[-0.589,-0.429],[0,0],[0,0],[-0.435,0.337],[-0.551,0.01]],"v":[[30.31,44.552],[-52.182,-20.402],[-52.182,-20.402],[-54.208,-21.061],[-53.211,-81.02],[33.366,44.495],[31.848,45.03]],"c":true}]},{"t":38,"s":[{"i":[[0.557,0.399],[0,0],[0,0],[0.906,0],[0,0],[0,0],[0.685,-0.013]],"o":[[0,0],[0,0],[-0.732,-0.533],[0,0],[0,0],[-0.541,0.419],[-0.685,0.013]],"v":[[50.65,77.777],[-51.93,-2.993],[-51.93,-2.993],[-54.45,-3.813],[-53.21,-78.373],[54.45,77.707],[52.562,78.372]],"c":true}]}],"ix":2},"nm":"Path 1","mn":"ADBE Vector Shape - Group","hd":false},{"ty":"fl","c":{"a":0,"k":[1,0.78,0.22,1],"ix":4,"x":"var $bm_rt;\n$bm_rt = comp('wired-flat-237-star-rating-morph').layer('control').effect('primary')('Color');"},"o":{"a":0,"k":100,"ix":5},"r":1,"bm":0,"nm":".primary","mn":"ADBE Vector Graphic - Fill","hd":false,"cl":"primary"},{"ty":"tr","p":{"a":0,"k":[141.812,28.094],"ix":2},"a":{"a":0,"k":[0,0],"ix":1},"s":{"a":0,"k":[100,100],"ix":3},"r":{"a":0,"k":0,"ix":6},"o":{"a":0,"k":100,"ix":7},"sk":{"a":0,"k":0,"ix":4},"sa":{"a":0,"k":0,"ix":5},"nm":"Transform"}],"nm":"Vector 3","np":2,"cix":2,"bm":0,"ix":2,"mn":"ADBE Vector Group","hd":false},{"ty":"gr","it":[{"ind":0,"ty":"sh","ix":1,"ks":{"a":1,"k":[{"i":{"x":0.318,"y":1},"o":{"x":0.333,"y":0},"t":0,"s":[{"i":[[0,0],[-0.629,0.397],[0,0],[-0.618,0.005],[0,0],[0,0],[-0.327,0.974]],"o":[[0.23,-0.708],[0,0],[0.527,-0.322],[0,0],[0,0],[0.875,-0.538],[0,0]],"v":[[18.7,-89.695],[20.03,-91.405],[20.03,-91.405],[21.78,-91.905],[22.93,91.905],[-22.93,35.445],[-21.07,33.105]],"c":true}]},{"i":{"x":0.667,"y":1},"o":{"x":0.688,"y":0},"t":8,"s":[{"i":[[0,0],[-0.695,0.439],[0,0],[-0.682,0.006],[0,0],[0,0],[-0.361,1.075]],"o":[[0.254,-0.781],[0,0],[0.582,-0.356],[0,0],[0,0],[0.965,-0.594],[0,0]],"v":[[36.66,-124.821],[38.129,-126.708],[38.129,-126.708],[40.06,-127.26],[41.33,75.632],[-9.291,13.311],[-7.238,10.728]],"c":true}]},{"i":{"x":0.667,"y":1},"o":{"x":0.333,"y":0},"t":22,"s":[{"i":[[0,0],[-0.506,0.32],[0,0],[-0.497,0.004],[0,0],[0,0],[-0.263,0.783]],"o":[[0.185,-0.569],[0,0],[0.424,-0.259],[0,0],[0,0],[0.703,-0.433],[0,0]],"v":[[19.53,-56.783],[20.6,-58.158],[20.6,-58.158],[22.007,-58.561],[22.932,89.255],[-13.948,43.851],[-12.452,41.97]],"c":true}]},{"t":38,"s":[{"i":[[0,0],[-0.629,0.397],[0,0],[-0.618,0.005],[0,0],[0,0],[-0.327,0.974]],"o":[[0.23,-0.708],[0,0],[0.527,-0.322],[0,0],[0,0],[0.875,-0.538],[0,0]],"v":[[18.7,-89.695],[20.03,-91.405],[20.03,-91.405],[21.78,-91.905],[22.93,91.905],[-22.93,35.445],[-21.07,33.105]],"c":true}]}],"ix":2},"nm":"Path 1","mn":"ADBE Vector Shape - Group","hd":false},{"ty":"fl","c":{"a":0,"k":[1,0.78,0.22,1],"ix":4,"x":"var $bm_rt;\n$bm_rt = comp('wired-flat-237-star-rating-morph').layer('control').effect('primary')('Color');"},"o":{"a":0,"k":100,"ix":5},"r":1,"bm":0,"nm":".primary","mn":"ADBE Vector Graphic - Fill","hd":false,"cl":"primary"},{"ty":"tr","p":{"a":0,"k":[65.656,-142.172],"ix":2},"a":{"a":0,"k":[0,0],"ix":1},"s":{"a":0,"k":[100,100],"ix":3},"r":{"a":0,"k":0,"ix":6},"o":{"a":0,"k":100,"ix":7},"sk":{"a":0,"k":0,"ix":4},"sa":{"a":0,"k":0,"ix":5},"nm":"Transform"}],"nm":"Vector 2","np":2,"cix":2,"bm":0,"ix":3,"mn":"ADBE Vector Group","hd":false},{"ty":"gr","it":[{"ind":0,"ty":"sh","ix":1,"ks":{"a":1,"k":[{"i":{"x":0.318,"y":1},"o":{"x":0.333,"y":0},"t":0,"s":[{"i":[[0.763,0.541],[0,0],[0,0],[0.217,0.659],[-0.227,0.656],[0,0],[0,0],[0.213,0.652],[-0.225,0.648],[0,0],[0.292,0.889]],"o":[[0,0],[0,0],[-0.572,-0.393],[-0.217,-0.659],[0,0],[0,0],[-0.564,-0.39],[-0.213,-0.652],[0,0],[0.295,-0.888],[-0.292,-0.889]],"v":[[14.957,-26.475],[-87.213,-100.155],[-87.213,-100.155],[-88.429,-101.777],[-88.413,-103.805],[88.587,-50.275],[-20.963,103.805],[-22.16,102.199],[-22.143,100.195],[16.577,-21.535],[16.582,-24.272]],"c":true}]},{"i":{"x":0.667,"y":1},"o":{"x":0.688,"y":0},"t":8,"s":[{"i":[[0.843,0.598],[0,0],[0,0],[0.239,0.728],[-0.251,0.724],[0,0],[0,0],[0.235,0.72],[-0.248,0.715],[0,0],[0.322,0.982]],"o":[[0,0],[0,0],[-0.631,-0.434],[-0.239,-0.728],[0,0],[0,0],[-0.622,-0.431],[-0.235,-0.72],[0,0],[0.325,-0.981],[-0.322,-0.982]],"v":[[25.713,-40.278],[-87.064,-121.607],[-87.064,-121.607],[-88.406,-123.398],[-88.389,-125.636],[106.987,-66.549],[-13.936,103.527],[-15.258,101.754],[-15.239,99.543],[27.501,-34.825],[27.506,-37.846]],"c":true}]},{"i":{"x":0.667,"y":1},"o":{"x":0.333,"y":0},"t":22,"s":[{"i":[[0.614,0.435],[0,0],[0,0],[0.174,0.53],[-0.183,0.527],[0,0],[0,0],[0.171,0.524],[-0.181,0.521],[0,0],[0.235,0.715]],"o":[[0,0],[0,0],[-0.46,-0.316],[-0.174,-0.53],[0,0],[0,0],[-0.453,-0.314],[-0.171,-0.524],[0,0],[0.237,-0.714],[-0.235,-0.715]],"v":[[29.378,-33.784],[-52.785,-93.036],[-52.785,-93.036],[-53.763,-94.34],[-53.75,-95.971],[88.589,-52.923],[0.492,70.984],[-0.472,69.692],[-0.457,68.081],[30.68,-29.811],[30.684,-32.012]],"c":true}]},{"t":38,"s":[{"i":[[0.763,0.541],[0,0],[0,0],[0.217,0.659],[-0.227,0.656],[0,0],[0,0],[0.213,0.652],[-0.225,0.648],[0,0],[0.292,0.889]],"o":[[0,0],[0,0],[-0.572,-0.393],[-0.217,-0.659],[0,0],[0,0],[-0.564,-0.39],[-0.213,-0.652],[0,0],[0.295,-0.888],[-0.292,-0.889]],"v":[[14.957,-26.475],[-87.213,-100.155],[-87.213,-100.155],[-88.429,-101.777],[-88.413,-103.805],[88.587,-50.275],[-20.963,103.805],[-22.16,102.199],[-22.143,100.195],[16.577,-21.535],[16.582,-24.272]],"c":true}]}],"ix":2},"nm":"Path 1","mn":"ADBE Vector Shape - Group","hd":false},{"ty":"fl","c":{"a":0,"k":[1,0.78,0.22,1],"ix":4,"x":"var $bm_rt;\n$bm_rt = comp('wired-flat-237-star-rating-morph').layer('control').effect('primary')('Color');"},"o":{"a":0,"k":100,"ix":5},"r":1,"bm":0,"nm":".primary","mn":"ADBE Vector Graphic - Fill","hd":false,"cl":"primary"},{"ty":"tr","p":{"a":0,"k":[0,0],"ix":2},"a":{"a":0,"k":[0,0],"ix":1},"s":{"a":0,"k":[100,100],"ix":3},"r":{"a":0,"k":0,"ix":6},"o":{"a":0,"k":100,"ix":7},"sk":{"a":0,"k":0,"ix":4},"sa":{"a":0,"k":0,"ix":5},"nm":"Transform"}],"nm":"Vector","np":2,"cix":2,"bm":0,"ix":4,"mn":"ADBE Vector Group","hd":false}],"ip":0,"op":300,"st":0,"ct":1,"bm":1},{"ddd":0,"ind":2,"ty":4,"nm":"Star","sr":1,"ks":{"o":{"a":0,"k":100,"ix":11},"r":{"a":1,"k":[{"i":{"x":[0.32],"y":[1]},"o":{"x":[0.333],"y":[0]},"t":0,"s":[0]},{"i":{"x":[0.667],"y":[1]},"o":{"x":[0.68],"y":[0]},"t":15,"s":[-33]},{"i":{"x":[0.667],"y":[1]},"o":{"x":[0.333],"y":[0]},"t":29,"s":[12]},{"i":{"x":[0.667],"y":[1]},"o":{"x":[0.333],"y":[0]},"t":45,"s":[-4]},{"t":60,"s":[0]}],"ix":10},"p":{"a":0,"k":[214.963,215.005,0],"ix":2,"l":2},"a":{"a":0,"k":[0,0,0],"ix":1,"l":2},"s":{"a":0,"k":[100,100,100],"ix":6,"l":2}},"ao":0,"shapes":[{"ty":"gr","it":[{"ind":0,"ty":"sh","ix":1,"ks":{"a":1,"k":[{"i":{"x":0.318,"y":1},"o":{"x":0.333,"y":0},"t":0,"s":[{"i":[[-0.924,-0.002],[0,0],[0,0],[-0.558,-0.406],[-0.21,-0.657],[0.22,-0.654],[0.564,-0.397],[0,0],[0.291,-0.899],[-0.297,-0.897],[0,0],[0.197,-0.658],[0.548,-0.415],[0.687,-0.012],[0.562,0.396],[0,0],[0.925,0],[0.749,-0.542],[0,0],[0.687,0],[0.555,0.404],[0.211,0.654],[-0.214,0.653],[0,0],[0.291,0.888],[0.76,0.545],[0,0],[0.213,0.652],[-0.211,0.652],[-0.554,0.404],[-0.686,0.002],[0,0],[-0.752,0.538],[-0.297,0.875],[0,0],[-0.553,0.398],[-0.681,-0.01],[-0.555,-0.396],[-0.21,-0.648],[0,0],[-0.751,-0.538]],"o":[[0,0],[0,0],[0.69,-0.003],[0.558,0.406],[0.21,0.657],[-0.22,0.654],[0,0],[-0.767,0.552],[-0.291,0.899],[0,0],[0.229,0.648],[-0.197,0.658],[-0.548,0.415],[-0.687,0.012],[0,0],[-0.749,-0.542],[-0.925,0],[0,0],[-0.556,0.404],[-0.687,0],[-0.555,-0.404],[-0.211,-0.654],[0,0],[0.29,-0.889],[-0.291,-0.888],[0,0],[-0.555,-0.403],[-0.213,-0.652],[0.211,-0.652],[0.554,-0.404],[0,0],[0.924,0.001],[0.752,-0.538],[0,0],[0.206,-0.649],[0.553,-0.398],[0.681,-0.012],[0.555,0.396],[0,0],[0.3,0.874],[0.751,0.538]],"v":[[46.477,-41.495],[173.947,-41.445],[173.947,-41.415],[175.868,-40.796],[177.05,-39.161],[177.034,-37.143],[175.827,-35.525],[71.957,38.545],[70.328,40.779],[70.337,43.545],[108.687,165.965],[108.737,167.975],[107.59,169.628],[105.69,170.285],[103.767,169.695],[1.187,88.935],[-1.388,88.1],[-3.963,88.935],[-105.783,167.635],[-107.695,168.256],[-109.607,167.634],[-110.787,166.005],[-110.783,163.995],[-72.063,42.265],[-72.065,39.53],[-73.683,37.325],[-175.863,-36.355],[-177.043,-37.978],[-177.046,-39.985],[-175.869,-41.61],[-173.963,-42.235],[-48.283,-42.275],[-45.705,-43.101],[-44.093,-45.275],[-4.273,-168.075],[-3.103,-169.688],[-1.203,-170.285],[0.7,-169.693],[1.877,-168.085],[42.287,-44.495],[43.903,-42.325]],"c":true}]},{"i":{"x":0.667,"y":1},"o":{"x":0.688,"y":0},"t":8,"s":[{"i":[[-1.021,-0.002],[0,0],[0,0],[-0.617,-0.448],[-0.232,-0.726],[0.243,-0.723],[0.623,-0.439],[0,0],[0.322,-0.994],[-0.329,-0.992],[0,0],[0.218,-0.728],[0.605,-0.459],[0.759,-0.013],[0.621,0.437],[0,0],[1.022,0],[0.828,-0.599],[0,0],[0.759,0],[0.614,0.447],[0.233,0.723],[-0.236,0.722],[0,0],[0.322,0.982],[0.84,0.602],[0,0],[0.235,0.72],[-0.233,0.721],[-0.612,0.447],[-0.758,0.002],[0,0],[-0.831,0.595],[-0.328,0.967],[0,0],[-0.611,0.44],[-0.753,0.013],[-0.613,-0.438],[-0.232,-0.716],[0,0],[-0.83,-0.594]],"o":[[0,0],[0,0],[0.762,-0.004],[0.617,0.448],[0.232,0.726],[-0.243,0.723],[0,0],[-0.848,0.61],[-0.322,0.994],[0,0],[0.253,0.716],[-0.218,0.728],[-0.605,0.459],[-0.759,0.013],[0,0],[-0.828,-0.599],[-1.022,0],[0,0],[-0.614,0.447],[-0.759,0],[-0.614,-0.447],[-0.233,-0.723],[0,0],[0.32,-0.982],[-0.322,-0.982],[0,0],[-0.613,-0.445],[-0.235,-0.72],[0.233,-0.721],[0.612,-0.447],[0,0],[1.022,0.001],[0.831,-0.595],[0,0],[0.228,-0.718],[0.611,-0.44],[0.753,-0.013],[0.613,0.438],[0,0],[0.331,0.966],[0.83,0.594]],"v":[[69.985,-63.749],[210.849,-63.693],[210.849,-63.66],[212.971,-62.976],[214.277,-61.168],[214.26,-58.938],[212.926,-57.151],[98.143,24.701],[96.342,27.171],[96.352,30.227],[138.732,165.509],[138.786,167.731],[137.52,169.557],[135.419,170.284],[133.295,169.631],[19.937,80.386],[17.091,79.464],[14.246,80.386],[-98.273,167.355],[-100.386,168.042],[-102.499,167.354],[-103.803,165.554],[-103.798,163.332],[-61.01,28.812],[-61.012,25.79],[-62.8,23.353],[-175.716,-58.068],[-177.021,-59.862],[-177.024,-62.079],[-175.724,-63.876],[-173.616,-64.566],[-34.731,-64.61],[-31.883,-65.523],[-30.101,-67.926],[13.903,-203.628],[15.195,-205.411],[17.296,-206.071],[19.398,-205.417],[20.699,-203.639],[65.355,-67.064],[67.14,-64.666]],"c":true}]},{"i":{"x":0.667,"y":1},"o":{"x":0.333,"y":0},"t":22,"s":[{"i":[[-0.74,-0.002],[0,0],[0,0],[-0.447,-0.325],[-0.168,-0.526],[0.176,-0.523],[0.452,-0.318],[0,0],[0.233,-0.72],[-0.238,-0.718],[0,0],[0.158,-0.527],[0.439,-0.332],[0.55,-0.01],[0.45,0.317],[0,0],[0.74,0],[0.6,-0.434],[0,0],[0.55,0],[0.445,0.324],[0.169,0.523],[-0.171,0.523],[0,0],[0.233,0.711],[0.608,0.436],[0,0],[0.17,0.522],[-0.169,0.522],[-0.443,0.324],[-0.549,0.002],[0,0],[-0.602,0.431],[-0.238,0.701],[0,0],[-0.443,0.319],[-0.546,0.009],[-0.444,-0.317],[-0.168,-0.519],[0,0],[-0.601,-0.431]],"o":[[0,0],[0,0],[0.552,-0.003],[0.447,0.325],[0.168,0.526],[-0.176,0.523],[0,0],[-0.614,0.442],[-0.233,0.72],[0,0],[0.184,0.519],[-0.158,0.527],[-0.439,0.332],[-0.55,0.01],[0,0],[-0.6,-0.434],[-0.74,0],[0,0],[-0.445,0.324],[-0.55,0],[-0.445,-0.324],[-0.169,-0.523],[0,0],[0.232,-0.712],[-0.233,-0.711],[0,0],[-0.444,-0.323],[-0.17,-0.522],[0.169,-0.522],[0.443,-0.324],[0,0],[0.74,0.001],[0.602,-0.431],[0,0],[0.165,-0.52],[0.443,-0.319],[0.546,-0.009],[0.444,0.317],[0,0],[0.24,0.7],[0.601,0.431]],"v":[[37.213,-33.223],[139.272,-33.183],[139.272,-33.159],[140.81,-32.664],[141.756,-31.354],[141.744,-29.738],[140.777,-28.443],[57.613,30.861],[56.309,32.65],[56.316,34.864],[87.021,132.88],[87.061,134.49],[86.143,135.813],[84.621,136.34],[83.082,135.867],[0.951,71.206],[-1.111,70.538],[-3.172,71.206],[-84.695,134.217],[-86.226,134.715],[-87.757,134.217],[-88.701,132.913],[-88.698,131.303],[-57.697,33.839],[-57.699,31.65],[-58.994,29.884],[-140.805,-29.108],[-141.75,-30.407],[-141.752,-32.014],[-140.81,-33.315],[-139.284,-33.816],[-38.657,-33.848],[-36.594,-34.509],[-35.303,-36.25],[-3.421,-134.57],[-2.484,-135.862],[-0.963,-136.34],[0.561,-135.866],[1.503,-134.578],[33.858,-35.625],[35.151,-33.888]],"c":true}]},{"t":38,"s":[{"i":[[-0.924,-0.002],[0,0],[0,0],[-0.558,-0.406],[-0.21,-0.657],[0.22,-0.654],[0.564,-0.397],[0,0],[0.291,-0.899],[-0.297,-0.897],[0,0],[0.197,-0.658],[0.548,-0.415],[0.687,-0.012],[0.562,0.396],[0,0],[0.925,0],[0.749,-0.542],[0,0],[0.687,0],[0.555,0.404],[0.211,0.654],[-0.214,0.653],[0,0],[0.291,0.888],[0.76,0.545],[0,0],[0.213,0.652],[-0.211,0.652],[-0.554,0.404],[-0.686,0.002],[0,0],[-0.752,0.538],[-0.297,0.875],[0,0],[-0.553,0.398],[-0.681,-0.01],[-0.555,-0.396],[-0.21,-0.648],[0,0],[-0.751,-0.538]],"o":[[0,0],[0,0],[0.69,-0.003],[0.558,0.406],[0.21,0.657],[-0.22,0.654],[0,0],[-0.767,0.552],[-0.291,0.899],[0,0],[0.229,0.648],[-0.197,0.658],[-0.548,0.415],[-0.687,0.012],[0,0],[-0.749,-0.542],[-0.925,0],[0,0],[-0.556,0.404],[-0.687,0],[-0.555,-0.404],[-0.211,-0.654],[0,0],[0.29,-0.889],[-0.291,-0.888],[0,0],[-0.555,-0.403],[-0.213,-0.652],[0.211,-0.652],[0.554,-0.404],[0,0],[0.924,0.001],[0.752,-0.538],[0,0],[0.206,-0.649],[0.553,-0.398],[0.681,-0.012],[0.555,0.396],[0,0],[0.3,0.874],[0.751,0.538]],"v":[[46.477,-41.495],[173.947,-41.445],[173.947,-41.415],[175.868,-40.796],[177.05,-39.161],[177.034,-37.143],[175.827,-35.525],[71.957,38.545],[70.328,40.779],[70.337,43.545],[108.687,165.965],[108.737,167.975],[107.59,169.628],[105.69,170.285],[103.767,169.695],[1.187,88.935],[-1.388,88.1],[-3.963,88.935],[-105.783,167.635],[-107.695,168.256],[-109.607,167.634],[-110.787,166.005],[-110.783,163.995],[-72.063,42.265],[-72.065,39.53],[-73.683,37.325],[-175.863,-36.355],[-177.043,-37.978],[-177.046,-39.985],[-175.869,-41.61],[-173.963,-42.235],[-48.283,-42.275],[-45.705,-43.101],[-44.093,-45.275],[-4.273,-168.075],[-3.103,-169.688],[-1.203,-170.285],[0.7,-169.693],[1.877,-168.085],[42.287,-44.495],[43.903,-42.325]],"c":true}]}],"ix":2},"nm":"Path 1","mn":"ADBE Vector Shape - Group","hd":false},{"ty":"fl","c":{"a":0,"k":[1,0.78,0.22,1],"ix":4,"x":"var $bm_rt;\n$bm_rt = comp('wired-flat-237-star-rating-morph').layer('control').effect('primary')('Color');"},"o":{"a":0,"k":100,"ix":5},"r":1,"bm":0,"nm":".primary","mn":"ADBE Vector Graphic - Fill","hd":false,"cl":"primary"},{"ty":"tr","p":{"a":0,"k":[0,0],"ix":2},"a":{"a":0,"k":[0,0],"ix":1},"s":{"a":0,"k":[100,100],"ix":3},"r":{"a":0,"k":0,"ix":6},"o":{"a":0,"k":100,"ix":7},"sk":{"a":0,"k":0,"ix":4},"sa":{"a":0,"k":0,"ix":5},"nm":"Transform"}],"nm":"Vector","np":2,"cix":2,"bm":0,"ix":1,"mn":"ADBE Vector Group","hd":false}],"ip":0,"op":300,"st":0,"ct":1,"bm":0}]}],"layers":[{"ddd":0,"ind":1,"ty":3,"nm":"control","sr":1,"ks":{"o":{"a":0,"k":0,"ix":11},"r":{"a":0,"k":0,"ix":10},"p":{"a":0,"k":[0,0],"ix":2,"l":2},"a":{"a":0,"k":[0,0,0],"ix":1,"l":2},"s":{"a":0,"k":[100,100,100],"ix":6,"l":2}},"ao":0,"ef":[{"ty":5,"nm":"primary","np":3,"mn":"ADBE Color Control","ix":1,"en":1,"ef":[{"ty":2,"nm":"Color","mn":"ADBE Color Control-0001","ix":1,"v":{"a":0,"k":[1,0.78,0.22],"ix":1}}]},{"ty":5,"nm":"secondary","np":3,"mn":"ADBE Color Control","ix":2,"en":1,"ef":[{"ty":2,"nm":"Color","mn":"ADBE Color Control-0001","ix":1,"v":{"a":0,"k":[0.227,0.2,0.278],"ix":1}}]},{"ty":5,"nm":"tertiary","np":3,"mn":"ADBE Color Control","ix":3,"en":1,"ef":[{"ty":2,"nm":"Color","mn":"ADBE Color Control-0001","ix":1,"v":{"a":0,"k":[0.922,0.902,0.937],"ix":1}}]}],"ip":0,"op":240,"st":0,"bm":0},{"ddd":0,"ind":3,"ty":0,"nm":"hover-pinch","refId":"comp_1","sr":1,"ks":{"o":{"a":0,"k":100,"ix":11},"r":{"a":0,"k":0,"ix":10},"p":{"a":0,"k":[215,215,0],"ix":2,"l":2},"a":{"a":0,"k":[215,215,0],"ix":1,"l":2},"s":{"a":0,"k":[100,100,100],"ix":6,"l":2}},"ao":0,"w":430,"h":430,"ip":0,"op":70,"st":0,"bm":0}],"markers":[{"tm":0,"cm":"default:hover-pinch","dr":60}]}